splitter.py
insta_splitter-0.1.dist-info/METADATA
insta_splitter-0.1.dist-info/WHEEL
insta_splitter-0.1.dist-info/entry_points.txt
insta_splitter-0.1.dist-info/top_level.txt
insta_splitter-0.1.dist-info/RECORD
