Metadata-Version: 2.1
Name: insta-splitter
Version: 0.1
Summary: A CLI tool for Instagram grid and stripes
Home-page: https://github.com/janmatzek/instagram-image-splitter
Author: janmatzek
Author-email: jan.matzek@gmail.com
Classifier: Programming Language :: Python :: 3
Classifier: License :: OSI Approved :: MIT License
Classifier: Operating System :: OS Independent
Requires-Python: >=3.6
Requires-Dist: pillow
